[{"Discipline":"Canoeing","value":0.2765957447},{"Discipline":"Fencing","value":0.2295081967},{"Discipline":"Cycling","value":0.161849711},{"Discipline":"Judo","value":0.1212121212},{"Discipline":"Handball","value":0.0833333333},{"Discipline":"Rowing","value":0.0833333333},{"Discipline":"Taekwondo","value":0.0701754386},{"Discipline":"Equestrian","value":0.0666666667},{"Discipline":"Sailing","value":0.052238806},{"Discipline":"Tennis","value":0.0454545455},{"Discipline":"Swimming","value":0.0399002494}]